MANIFEST.in
README.md
setup.py
pydotask.egg-info/PKG-INFO
pydotask.egg-info/SOURCES.txt
pydotask.egg-info/dependency_links.txt
pydotask.egg-info/entry_points.txt
pydotask.egg-info/not-zip-safe
pydotask.egg-info/top_level.txt
task_mod/__init__.py
task_mod/pydo.py
task_mod/taskhandler.py
task_mod/tasks.csv
task_mod/styles/__init__.py
task_mod/styles/termcolor.py
task_mod/styles/text_style.py