Metadata-Version: 1.2
Name: pydotask
Version: 0.4.1
Summary: PyDo is a CLI Application to keep you on track with your tasks and projects
Home-page: UNKNOWN
Author: Abhishta Gatya
Author-email: abhishtagatya@yahoo.com
License: UNKNOWN
Keywords: utilities office schedule task reminder
Platform: UNKNOWN
Classifier: Development Status :: 3 - Alpha
Classifier: Programming Language :: Python :: 3.5
Classifier: Topic :: Office/Business :: Scheduling
Requires-Python: >=3
